botok/__init__.py
botok/config.py
botok/vars.py
botok/chunks/__init__.py
botok/chunks/chunkframework.py
botok/chunks/chunkframeworkbase.py
botok/chunks/chunks.py
botok/modifytokens/__init__.py
botok/modifytokens/adjusttokens.py
botok/modifytokens/cqlmatcher.py
botok/modifytokens/mergedagdra.py
botok/modifytokens/mergingmatcher.py
botok/modifytokens/replacingmatcher.py
botok/modifytokens/splitaffixed.py
botok/modifytokens/splittingmatcher.py
botok/modifytokens/tokenmerge.py
botok/modifytokens/tokensplit.py
botok/resources/README.md
botok/resources/SylComponents.json
botok/resources/bo_punct_position.csv
botok/resources/bo_uni_table.csv
botok/resources/particles.tsv
botok/text/__init__.py
botok/text/format.py
botok/text/modify.py
botok/text/pipelinebase.py
botok/text/preprocess.py
botok/text/text.py
botok/text/tokenize.py
botok/textunits/__init__.py
botok/textunits/bostring.py
botok/textunits/bosyl.py
botok/textunits/charcategories.py
botok/textunits/sylcomponents.py
botok/third_party/__init__.py
botok/third_party/cqlparser.py
botok/third_party/has_skrt_syl.py
botok/third_party/pynpl/__init__.py
botok/third_party/pynpl/cql.py
botok/third_party/pynpl/fsa.py
botok/tokenizers/__init__.py
botok/tokenizers/chunktokenizer.py
botok/tokenizers/paragraphtokenizer.py
botok/tokenizers/sentencetokenizer.py
botok/tokenizers/stacktokenizer.py
botok/tokenizers/token.py
botok/tokenizers/tokenize.py
botok/tokenizers/wordtokenizer.py
botok/tries/__init__.py
botok/tries/basictrie.py
botok/tries/trie.py
botok/utils/__init__.py
botok/utils/corpus_normalization.py
botok/utils/expose_data.py
botok/utils/helpers.py
botok/utils/lenient_normalization.py
botok/utils/unicode_normalization.py
botok-1.1.2.dist-info/licenses/LICENSE
botok-1.1.2.dist-info/METADATA
botok-1.1.2.dist-info/WHEEL
botok-1.1.2.dist-info/top_level.txt
botok-1.1.2.dist-info/RECORD
