Metadata-Version: 2.4
Name: botok
Version: 1.1.2
Summary: Tibetan Word Tokenizer
Home-page: https://github.com/OpenPecha/botok
Author: OpenPecha development team
Author-email: openpecha@gmail.com
License: Apache2
Project-URL: Source, https://github.com/OpenPecha/botok
Project-URL: Tracker, https://github.com/OpenPecha/botok/issues
Keywords: nlp computational_linguistics tibetan tokenizer token
Classifier: Development Status :: 3 - Alpha
Classifier: Topic :: Text Processing :: Linguistic
Classifier: Programming Language :: Python :: 3
Classifier: Operating System :: OS Independent
Classifier: Intended Audience :: Developers
Classifier: Intended Audience :: Science/Research
Classifier: License :: OSI Approved :: Apache Software License
Classifier: Natural Language :: Tibetan
Requires-Python: >=3.7
License-File: LICENSE
Requires-Dist: pyyaml
Requires-Dist: requests
Dynamic: author
Dynamic: author-email
Dynamic: classifier
Dynamic: description
Dynamic: description-content-type
Dynamic: home-page
Dynamic: keywords
Dynamic: license
Dynamic: license-file
Dynamic: project-url
Dynamic: requires-dist
Dynamic: requires-python
Dynamic: summary
